sigscale_ocs/__init__.py
sigscale_ocs/balance.py
sigscale_ocs/client.py
sigscale_ocs/exceptions.py
sigscale_ocs/models.py
sigscale_ocs/product_catalog.py
sigscale_ocs/product_inventory.py
sigscale_ocs/service_inventory.py
sigscale_ocs_api-0.1.0.dist-info/licenses/LICENSE
sigscale_ocs_api-0.1.0.dist-info/METADATA
sigscale_ocs_api-0.1.0.dist-info/WHEEL
sigscale_ocs_api-0.1.0.dist-info/top_level.txt
sigscale_ocs_api-0.1.0.dist-info/RECORD
