Metadata-Version: 2.4
Name: sigscale-ocs-api
Version: 0.1.0
Summary: A Python client for the Sigscale OCS API
Author-email: Keegan White <keeganthomaswhite@gmail.com>
License-Expression: GPL-3.0-or-later
Project-URL: Homepage, https://github.com/keeganwhite/sigscale-ocs-api
Project-URL: Bug Reports, https://github.com/keeganwhite/sigscale-ocs-api/issues
Project-URL: Source, https://github.com/keeganwhite/sigscale-ocs-api
Project-URL: Documentation, https://github.com/keeganwhite/sigscale-ocs-api#readme
Keywords: sigscale,ocs,api,telecom,billing,tmf,openapi
Classifier: Development Status :: 4 - Beta
Classifier: Intended Audience :: Developers
Classifier: Operating System :: OS Independent
Classifier: Programming Language :: Python :: 3
Classifier: Programming Language :: Python :: 3.9
Classifier: Programming Language :: Python :: 3.10
Classifier: Programming Language :: Python :: 3.11
Classifier: Programming Language :: Python :: 3.12
Classifier: Topic :: Software Development :: Libraries :: Python Modules
Classifier: Topic :: Communications :: Telephony
Classifier: Topic :: Internet :: WWW/HTTP :: Dynamic Content
Requires-Python: >=3.9
License-File: LICENSE
Requires-Dist: requests>=2.25.1
Requires-Dist: python-dotenv>=0.19.0
Provides-Extra: dev
Requires-Dist: pytest>=6.2.4; extra == "dev"
Requires-Dist: pytest-cov>=2.12.1; extra == "dev"
Requires-Dist: flake8>=3.9.2; extra == "dev"
Requires-Dist: mypy>=0.910; extra == "dev"
Requires-Dist: black>=21.5b2; extra == "dev"
Requires-Dist: types-requests>=2.25.0; extra == "dev"
Dynamic: license-file
